type_enforcer/__init__.py
type_enforcer/enforcer.py
divine_type_enforcer-0.1.13.dist-info/METADATA
divine_type_enforcer-0.1.13.dist-info/WHEEL
divine_type_enforcer-0.1.13.dist-info/licenses/LICENSE
divine_type_enforcer-0.1.13.dist-info/RECORD
