Metadata-Version: 2.4
Name: divine-type-enforcer
Version: 0.1.13
Summary: A runtime type validation utility with detailed error reporting.
Project-URL: Homepage, https://github.com/divinescreener/type-enforcer
Project-URL: Issues, https://github.com/divinescreener/type-enforcer/issues
Author-email: DIVINE <admin@divine.sh>
License: MIT
License-File: LICENSE
Requires-Python: >=3.13
